dummy_pkg/__init__.py
dummy_pkg/utils.py
dummy_pkg-0.1.0.dist-info/WHEEL
dummy_pkg-0.1.0.dist-info/METADATA
dummy_pkg-0.1.0.dist-info/RECORD
