Metadata-Version: 2.1
Name: dummy-pkg
Version: 0.1.0
Summary: 
Author: glaunay
Author-email: pitooon@gmail.com
Requires-Python: >=3.9,<3.11
Classifier: Programming Language :: Python :: 3
Classifier: Programming Language :: Python :: 3.10
Classifier: Programming Language :: Python :: 3.9
Requires-Dist: scipy (>=1.8.1,<2.0.0)
